{"index.css":"/* css */","map-data/marker-cluster.json":"{\r\n    \"cluster\": [\r\n        {\r\n            \"latitude\": 40.6971494,\r\n            \"longitude\": -74.2598747,\r\n            \"city\": \"New York\",\r\n            \"area\": 8683,\r\n            \"Rank\": 1\r\n        },\r\n        {\r\n            \"latitude\": 35.4526439,\r\n            \"longitude\": 139.4567198,\r\n            \"city\": \"Tokyo\",\r\n            \"area\": 6993,\r\n            \"Rank\": 2\r\n        },\r\n        {\r\n            \"latitude\": 41.8333925,\r\n            \"longitude\": -88.0121569,\r\n            \"city\": \"Chicago\",\r\n            \"area\": 5498,\r\n            \"Rank\": 3\r\n        },\r\n        {\r\n            \"latitude\": 33.1147951,\r\n            \"longitude\": -94.2114611,\r\n            \"city\": \"Atlanta\",\r\n            \"area\": 5083,\r\n            \"Rank\": 4\r\n        },\r\n        {\r\n            \"latitude\": 40.0024137,\r\n            \"longitude\": -75.2581194,\r\n            \"city\": \"Philadelphia\",\r\n            \"area\": 4661,\r\n            \"Rank\": 5\r\n        },\r\n        {\r\n            \"latitude\": 42.3142647,\r\n            \"longitude\": -71.11037,\r\n            \"city\": \"Boston\",\r\n            \"area\": 4497,\r\n            \"Rank\": 6\r\n        },\r\n        {\r\n            \"latitude\": 34.0201613,\r\n            \"longitude\": -118.6919306,\r\n            \"city\": \"Los Angeles\",\r\n            \"area\": 4320,\r\n            \"Rank\": 7\r\n        },\r\n        {\r\n            \"latitude\": 32.8203525,\r\n            \"longitude\": -97.0117413,\r\n            \"city\": \"Dallas\",\r\n            \"area\": 3644,\r\n            \"Rank\": 8\r\n        },\r\n        {\r\n            \"latitude\": 31.2590796,\r\n            \"longitude\": -95.6476923,\r\n            \"city\": \"Houston\",\r\n            \"area\": 3355,\r\n            \"Rank\": 9\r\n        },\r\n        {\r\n            \"latitude\": 42.3526257,\r\n            \"longitude\": -83.239291,\r\n            \"city\": \"Detroit\",\r\n            \"area\": 3267,\r\n            \"Rank\": 10\r\n        },\r\n        {\r\n            \"latitude\": 47.2510905,\r\n            \"longitude\": -123.1255834,\r\n            \"city\": \"Washington\",\r\n            \"area\": 2996,\r\n            \"Rank\": 11\r\n        },\r\n        {\r\n            \"latitude\": 25.7823907,\r\n            \"longitude\": -80.2994995,\r\n            \"city\": \"Miami\",\r\n            \"area\": 2891,\r\n            \"Rank\": 12\r\n        },\r\n        {\r\n            \"latitude\": 35.1468253,\r\n            \"longitude\": 136.7862238,\r\n            \"city\": \"Nagoya\",\r\n            \"area\": 2875,\r\n            \"Rank\": 13\r\n        },\r\n        {\r\n            \"latitude\": 48.8588377,\r\n            \"longitude\": 2.2770198,\r\n            \"city\": \"Paris\",\r\n            \"area\": 2723,\r\n            \"Rank\": 14\r\n        },\r\n        {\r\n            \"latitude\": 50.1781141,\r\n            \"longitude\": 2.4939991,\r\n            \"city\": \"Essen\",\r\n            \"area\": 2642,\r\n            \"Rank\": 15\r\n        },\r\n        {\r\n            \"latitude\": 34.677518,\r\n            \"longitude\": 135.3455988,\r\n            \"city\": \"Osaka\",\r\n            \"area\": 2564,\r\n            \"Rank\": 16\r\n        },\r\n        {\r\n            \"latitude\": 47.6129432,\r\n            \"longitude\": -122.4821496,\r\n            \"city\": \"Seattle\",\r\n            \"area\": 2470,\r\n            \"Rank\": 17\r\n        },\r\n        {\r\n            \"latitude\": -26.1715046,\r\n            \"longitude\": 27.9699835,\r\n            \"city\": \"Johannesburg\",\r\n            \"area\": 2396,\r\n            \"Rank\": 18\r\n        },\r\n        {\r\n            \"latitude\": 44.9706114,\r\n            \"longitude\": -93.4015641,\r\n            \"city\": \"Minneapolis\",\r\n            \"area\": 2316,\r\n            \"Rank\": 19\r\n        },\r\n        {\r\n            \"latitude\": 19.3892246,\r\n            \"longitude\": -70.1305136,\r\n            \"city\": \"San Juan\",\r\n            \"area\": 2309,\r\n            \"Rank\": 20\r\n        },\r\n        {\r\n            \"latitude\": -34.6157437,\r\n            \"longitude\": -60.5733857,\r\n            \"city\": \"Buenos Aires\",\r\n            \"area\": 2266,\r\n            \"Rank\": 21\r\n        },\r\n        {\r\n            \"latitude\": 40.4313473,\r\n            \"longitude\": -80.050541,\r\n            \"city\": \"Pittsburgh\",\r\n            \"area\": 2208,\r\n            \"Rank\": 22\r\n        },\r\n        {\r\n            \"latitude\": 55.580748,\r\n            \"longitude\": 36.8251027,\r\n            \"city\": \"Moscow\",\r\n            \"area\": 2150,\r\n            \"Rank\": 23\r\n        },\r\n        {\r\n            \"latitude\": 38.6530169,\r\n            \"longitude\": -90.3835487,\r\n            \"city\": \"St. Louis\",\r\n            \"area\": 2147,\r\n            \"Rank\": 24\r\n        },\r\n        {\r\n            \"latitude\": -37.9712368,\r\n            \"longitude\": 144.4926562,\r\n            \"city\": \"Melbourne\",\r\n            \"area\": 2080,\r\n            \"Rank\": 25\r\n        },\r\n        {\r\n            \"latitude\": 27.9941986,\r\n            \"longitude\": -82.7344819,\r\n            \"city\": \"Tampa\",\r\n            \"area\": 2078,\r\n            \"Rank\": 26\r\n        },\r\n        {\r\n            \"latitude\": 23.29296,\r\n            \"longitude\": -105.6587494,\r\n            \"city\": \"Mexico\",\r\n            \"area\": 2072,\r\n            \"Rank\": 27\r\n        },\r\n        {\r\n            \"latitude\": 13.0555127,\r\n            \"longitude\": 80.1330167,\r\n            \"city\": \"Phoenix\",\r\n            \"area\": 2069,\r\n            \"Rank\": 28\r\n        },\r\n        {\r\n            \"latitude\": 32.8242404,\r\n            \"longitude\": -117.3891773,\r\n            \"city\": \"San Diego\",\r\n            \"area\": 2026,\r\n            \"Rank\": 29\r\n        },\r\n        {\r\n            \"latitude\": -23.6821604,\r\n            \"longitude\": -46.8755027,\r\n            \"city\": \"Sao Paulo\",\r\n            \"area\": 1968,\r\n            \"Rank\": 30\r\n        },\r\n        {\r\n            \"latitude\": 39.2846225,\r\n            \"longitude\": -76.7605725,\r\n            \"city\": \"Baltimore\",\r\n            \"area\": 1768,\r\n            \"Rank\": 31\r\n        },\r\n        {\r\n            \"latitude\": 39.1362562,\r\n            \"longitude\": -84.680488,\r\n            \"city\": \"Cincinnati\",\r\n            \"area\": 1740,\r\n            \"Rank\": 32\r\n        },\r\n        {\r\n            \"latitude\": 45.5576996,\r\n            \"longitude\": -74.0104927,\r\n            \"city\": \"Montreal\",\r\n            \"area\": 1740,\r\n            \"Rank\": 33\r\n        },\r\n        {\r\n            \"latitude\": -33.3465295,\r\n            \"longitude\": 134.409569,\r\n            \"city\": \"Sydney\",\r\n            \"area\": 1687,\r\n            \"Rank\": 34\r\n        },\r\n        {\r\n            \"latitude\": 41.497447,\r\n            \"longitude\": -81.8459461,\r\n            \"city\": \"Cleveland\",\r\n            \"area\": 1676,\r\n            \"Rank\": 35\r\n        },\r\n        {\r\n            \"latitude\": 43.6565353,\r\n            \"longitude\": -79.6010416,\r\n            \"city\": \"Toronto\",\r\n            \"area\": 1655,\r\n            \"Rank\": 36\r\n        },\r\n        {\r\n            \"latitude\": 51.528308,\r\n            \"longitude\": 0.3817841,\r\n            \"city\": \"London\",\r\n            \"area\": 1623,\r\n            \"Rank\": 37\r\n        },\r\n        {\r\n            \"latitude\": 3.1384965,\r\n            \"longitude\": 101.5468996,\r\n            \"city\": \"Kuala Lumpur\",\r\n            \"area\": 1606,\r\n            \"Rank\": 38\r\n        },\r\n        {\r\n            \"latitude\": -27.3810232,\r\n            \"longitude\": 152.4326904,\r\n            \"city\": \"Brisbane\",\r\n            \"area\": 1603,\r\n            \"Rank\": 39\r\n        },\r\n        {\r\n            \"latitude\": -22.913885,\r\n            \"longitude\": -43.7261859,\r\n            \"city\": \"Rio de Janeiro\",\r\n            \"area\": 1580,\r\n            \"Rank\": 40\r\n        },\r\n        {\r\n            \"latitude\": 45.4626482,\r\n            \"longitude\": 9.0376468,\r\n            \"city\": \"Milan\",\r\n            \"area\": 1554,\r\n            \"Rank\": 41\r\n        },\r\n        {\r\n            \"latitude\": 38.477368,\r\n            \"longitude\": -100.564023,\r\n            \"city\": \"Kansas\",\r\n            \"area\": 1514,\r\n            \"Rank\": 42\r\n        },\r\n        {\r\n            \"latitude\": 39.7797003,\r\n            \"longitude\": -86.2728365,\r\n            \"city\": \"Indianapolis\",\r\n            \"area\": 1432,\r\n            \"Rank\": 43\r\n        },\r\n        {\r\n            \"latitude\": 14.5964957,\r\n            \"longitude\": 120.94454,\r\n            \"city\": \"Manila\",\r\n            \"area\": 1399,\r\n            \"Rank\": 44\r\n        },\r\n        {\r\n            \"latitude\": 37.7576793,\r\n            \"longitude\": -122.5076406,\r\n            \"city\": \"San Francisco\",\r\n            \"area\": 1365,\r\n            \"Rank\": 45\r\n        },\r\n        {\r\n            \"latitude\": 36.7953408,\r\n            \"longitude\": -76.2928249,\r\n            \"city\": \"Virginia Beach\",\r\n            \"area\": 1364,\r\n            \"Rank\": 46\r\n        },\r\n        {\r\n            \"latitude\": -6.229728,\r\n            \"longitude\": 106.6894282,\r\n            \"city\": \"Jakarta\",\r\n            \"area\": 1360,\r\n            \"Rank\": 47\r\n        },\r\n        {\r\n            \"latitude\": 41.8169712,\r\n            \"longitude\": -71.4912209,\r\n            \"city\": \"Providence\",\r\n            \"area\": 1304,\r\n            \"Rank\": 48\r\n        },\r\n        {\r\n            \"latitude\": 30.0594699,\r\n            \"longitude\": 31.1884235,\r\n            \"city\": \"Cairo\",\r\n            \"area\": 1295,\r\n            \"Rank\": 49\r\n        },\r\n        {\r\n            \"latitude\": 28.6466772,\r\n            \"longitude\": 76.8130623,\r\n            \"city\": \"Delhi\",\r\n            \"area\": 1295,\r\n            \"Rank\": 50\r\n        }\r\n    ]\r\n}\r\n","index.html":"<!DOCTYPE html>\r\n<html>\r\n<head>\r\n    <title>Syncfusion React Sample</title>\r\n    <meta charset=\"utf-8\" />\r\n    <meta name=\"viewport\" content=\"width=device-width, initial-scale=1.0, user-scalable=no\" />\r\n    <meta http-equiv=\"x-ua-compatible\" content=\"ie=edge\">\r\n    <meta name=\"description\" content=\"Syncfusion React UI Components\" />\r\n    <meta name=\"author\" content=\"Syncfusion\" />\r\n    <link href=\"////npmci.syncfusion.com/packages/development/{{theme}}.css\" rel=\"stylesheet\">\r\n    <link href=\"https://maxcdn.bootstrapcdn.com/bootstrap/3.3.7/css/bootstrap.min.css\" rel=\"stylesheet\" />\r\n</head>\r\n\r\n<body class=\"{{theme}}\">\r\n    <div id='sample'>\r\n</body>\r\n</html>\r\n","index.js":"import { render } from 'react-dom';\nimport './index.css';\n/**\r\n * Marker cluster map sample\r\n */\r\nimport * as React from \"react\";\r\nimport { MapAjax } from '@syncfusion/ej2-maps';\r\nimport { MapsComponent, Inject, LayersDirective, LayerDirective, MarkersDirective, MarkerDirective, Marker, Zoom, MapsTooltip } from '@syncfusion/ej2-react-maps';\r\nimport { SampleBase } from './sample-base';\r\nimport * as data from './map-data/marker-cluster.json';\r\nlet datasource = data;\r\nconst SAMPLE_CSS = `\r\n    .control-fluid {\r\n\t\tpadding: 0px !important;\r\n    }`;\r\nexport class MarkerCluster extends SampleBase {\r\n    render() {\r\n        return (<div className='control-panel'>\r\n                <style>\r\n                    {SAMPLE_CSS}\r\n                </style>\r\n                <div className='control-section'>\r\n                    <MapsComponent id=\"maps\" load={this.load} useGroupingSeparator={true} format='n' zoomSettings={{\r\n            enable: true\r\n        }} titleSettings={{\r\n            text: 'Top 50 largest cities in the World',\r\n            textStyle: {\r\n                size: '16px'\r\n            }\r\n        }}>\r\n                        <Inject services={[Marker, MapsTooltip, Zoom]}/>\r\n                        <LayersDirective>\r\n                            <LayerDirective shapeData={new MapAjax('////npmci.syncfusion.com/development/react/demos/src/maps/map-data/world-map.json')} shapeSettings={{\r\n            fill: '#C1DFF5'\r\n        }} markerClusterSettings={{\r\n            allowClustering: true,\r\n            shape: 'Image',\r\n            height: 40,\r\n            width: 40,\r\n            labelStyle: { color: 'white' },\r\n            imageUrl: '////npmci.syncfusion.com/development/react/demos/src/maps/images/cluster.svg'\r\n        }}>\r\n                                <MarkersDirective>\r\n                                    <MarkerDirective visible={true} dataSource={datasource.cluster} shape='Image' imageUrl='////npmci.syncfusion.com/development/react/demos/src/maps/images/ballon.png' tooltipSettings={{\r\n            visible: true,\r\n            valuePath: 'area',\r\n            template: '<div id=\"template\" style=\"width: 140px;opacity: 90%;background: rgba(53, 63, 76, 0.90);box-shadow: 0px 2px 2px rgba(0, 0, 0, 0.40);padding:10px;border: 1px #abb9c6;border-radius: 4px;\">' +\r\n                '<div style=\"font-size:13px;color:#ffffff;font-weight: 500;\"><center>${city}</center></div>' +\r\n                '<hr style=\"margin-top: 2px;margin-bottom:5px;border:0.5px solid #DDDDDD\">' +\r\n                '<div><span style=\"font-size:13px;color:#cccccc\">Rank : </span><span style=\"font-size:13px;color:#ffffff;font-weight: 500;\">${Rank}</span></div>' +\r\n                '<div><span style=\"font-size:13px;color:#cccccc\">Area : </span><span style=\"font-size:13px;color:#ffffff;font-weight: 500;\">${area} sq kms</span></div></div>',\r\n        }} height={20} width={20} animationDuration={0}>\r\n                                    </MarkerDirective>\r\n                                </MarkersDirective>\r\n                            </LayerDirective>\r\n                        </LayersDirective>\r\n                    </MapsComponent>\r\n                </div>\r\n                \r\n                <div style={{ float: 'right', marginright: '10px' }}>Source:\r\n       <a href=\"http://www.citymayors.com/statistics/largest-cities-population-125.html\" target=\"_blank\">www.citymayors.com</a>\r\n                </div>\r\n            </div>);\r\n    }\r\n}\r\n\nrender(<MarkerCluster />, document.getElementById('sample'));","sample-base.js":"import * as React from 'react';\n    {{ripple}}\n    export class SampleBase extends React.PureComponent {\n        rendereComplete() {\n            /**custom render complete function */\n        }\n        componentDidMount() {\n            setTimeout(() => {\n            this.rendereComplete();\n        });\n          }\n        }\n    ","dependencies":"{\"@syncfusion/ej2\": \"*\",\"@syncfusion/ej2-react-base\": \"*\",\"@syncfusion/ej2-react-buttons\": \"*\",\"@syncfusion/ej2-react-calendars\": \"*\",\"@syncfusion/ej2-react-charts\": \"*\",\"@syncfusion/ej2-react-diagrams\": \"*\",\"@syncfusion/ej2-react-circulargauge\": \"*\",\"@syncfusion/ej2-react-dropdowns\": \"*\",\"@syncfusion/ej2-react-filemanager\": \"*\",\"@syncfusion/ej2-react-grids\": \"*\",\"@syncfusion/ej2-react-inputs\": \"*\",\"@syncfusion/ej2-react-layouts\": \"*\",\"@syncfusion/ej2-react-lineargauge\": \"*\",\"@syncfusion/ej2-react-barcode-generator\": \"*\",\"@syncfusion/ej2-react-lists\": \"*\",\"@syncfusion/ej2-react-maps\": \"*\",\"@syncfusion/ej2-react-treemap\": \"*\",\"@syncfusion/ej2-react-heatmap\": \"*\",\"@syncfusion/ej2-react-navigations\": \"*\",\"@syncfusion/ej2-react-notifications\": \"*\",\"@syncfusion/ej2-react-inplace-editor\": \"*\",\"@syncfusion/ej2-react-treegrid\": \"*\",\"@syncfusion/ej2-react-popups\": \"*\",\"@syncfusion/ej2-react-schedule\": \"*\",\"@syncfusion/ej2-react-splitbuttons\": \"*\",\"@syncfusion/ej2-react-documenteditor\": \"*\",\"@syncfusion/ej2-react-richtexteditor\": \"*\",\"@syncfusion/ej2-react-pivotview\": \"*\",\"@syncfusion/ej2-react-pdfviewer\": \"*\",\"@syncfusion/ej2-react-querybuilder\": \"*\",\"@syncfusion/ej2-react-gantt\": \"*\",\"@syncfusion/ej2-react-spreadsheet\": \"*\"}"}